volttron/auth/auth_service.py
volttron/auth/authz_manager.py
volttron/auth/commands.py
volttron/auth/credential_manager.py
volttron/py.typed
volttron_lib_auth-2.0.0rc6.dist-info/LICENSE
volttron_lib_auth-2.0.0rc6.dist-info/METADATA
volttron_lib_auth-2.0.0rc6.dist-info/WHEEL
volttron_lib_auth-2.0.0rc6.dist-info/RECORD
