Metadata-Version: 2.3
Name: volttron-lib-auth
Version: 2.0.0rc6
Summary: Base Authentication Library for VOLTTRON
License: Apache-2.0
Author: C. Allwardt
Author-email: 3979063+craig8@users.noreply.github.com
Requires-Python: >=3.10,<4.0
Classifier: Intended Audience :: Developers
Classifier: Intended Audience :: Information Technology
Classifier: Intended Audience :: Other Audience
Classifier: Intended Audience :: Science/Research
Classifier: License :: OSI Approved :: Apache Software License
Classifier: Programming Language :: Python :: 3
Classifier: Programming Language :: Python :: 3.10
Classifier: Programming Language :: Python :: 3.11
Classifier: Programming Language :: Python :: 3.12
Classifier: Programming Language :: Python :: 3.13
Classifier: Programming Language :: Python :: 3 :: Only
Requires-Dist: volttron-core (>=2.0.0rc13)
Project-URL: Homepage, https://github.com/eclipse-volttron/volttron-lib-auth
Project-URL: Repository, https://github.com/eclipse-volttron/volttron-lib-auth
